odoo/addons/stay/README.rst
odoo/addons/stay/__init__.py
odoo/addons/stay/__manifest__.py
odoo/addons/stay/data/cron.xml
odoo/addons/stay/data/ir_config_parameter.xml
odoo/addons/stay/data/mail_template.xml
odoo/addons/stay/data/sequence.xml
odoo/addons/stay/demo/stay_demo.xml
odoo/addons/stay/i18n/fr.po
odoo/addons/stay/i18n/it.po
odoo/addons/stay/i18n/stay.pot
odoo/addons/stay/i18n/zh_CN.po
odoo/addons/stay/migrations/14.0.1.0.0/post-migration.py
odoo/addons/stay/migrations/14.0.1.0.0/pre-migration.py
odoo/addons/stay/migrations/14.0.4.0.1/pre-migration.py
odoo/addons/stay/models/__init__.py
odoo/addons/stay/models/res_company.py
odoo/addons/stay/models/res_partner.py
odoo/addons/stay/models/res_users.py
odoo/addons/stay/models/stay.py
odoo/addons/stay/models/stay_building.py
odoo/addons/stay/models/stay_tag.py
odoo/addons/stay/readme/CONFIGURE.rst
odoo/addons/stay/readme/CONTRIBUTORS.rst
odoo/addons/stay/readme/DESCRIPTION.rst
odoo/addons/stay/readme/USAGE.rst
odoo/addons/stay/report/report.xml
odoo/addons/stay/report/report_stay_journal.xml
odoo/addons/stay/security/ir.model.access.csv
odoo/addons/stay/security/stay_security.xml
odoo/addons/stay/static/description/icon.png
odoo/addons/stay/static/description/index.html
odoo/addons/stay/static/src/css/stay_iframe_style.css
odoo/addons/stay/tests/__init__.py
odoo/addons/stay/tests/test_stay.py
odoo/addons/stay/views/res_partner.xml
odoo/addons/stay/views/res_users.xml
odoo/addons/stay/views/stay.xml
odoo/addons/stay/views/stay_building.xml
odoo/addons/stay/views/stay_menu.xml
odoo/addons/stay/views/stay_tag.xml
odoo/addons/stay/wizard/__init__.py
odoo/addons/stay/wizard/res_config_settings.py
odoo/addons/stay/wizard/res_config_settings_view.xml
odoo/addons/stay/wizard/stay_fire_print.py
odoo/addons/stay/wizard/stay_fire_print_view.xml
odoo/addons/stay/wizard/stay_journal_print.py
odoo/addons/stay/wizard/stay_journal_print_view.xml
odoo/addons/stay/wizard/stay_line_mass_update.py
odoo14_addon_stay-14.0.5.1.0.dist-info/METADATA
odoo14_addon_stay-14.0.5.1.0.dist-info/WHEEL
odoo14_addon_stay-14.0.5.1.0.dist-info/top_level.txt
odoo14_addon_stay-14.0.5.1.0.dist-info/RECORD
