Metadata-Version: 2.1
Name: odoo14-addon-stay
Version: 14.0.5.1.0
Summary: Simple management of stays and meals
Home-page: https://github.com/OCA/vertical-abbey
Author: Barroux Abbey, Akretion, Odoo Community Association (OCA)
Author-email: support@odoo-community.org
License: AGPL-3
Classifier: Programming Language :: Python
Classifier: Framework :: Odoo
Classifier: Framework :: Odoo :: 14.0
Classifier: License :: OSI Approved :: GNU Affero General Public License v3
Requires-Python: >=3.6
Requires-Dist: odoo14-addon-web-timeline
Requires-Dist: odoo<14.1dev,>=14.0a
Requires-Dist: xlsxwriter
